clickomat.py
clickomat-1.0.7.dist-info/LICENSE
clickomat-1.0.7.dist-info/METADATA
clickomat-1.0.7.dist-info/WHEEL
clickomat-1.0.7.dist-info/entry_points.txt
clickomat-1.0.7.dist-info/top_level.txt
clickomat-1.0.7.dist-info/RECORD
