Metadata-Version: 2.1
Name: clickomat
Version: 1.0.7
Summary: Python-Script for automated click-sequences and text entry
Home-page: https://github.com/skilleven/clickomat
Author: skilleven (Torsten Hoeltge)
Author-email: <hello@skilleven.com>
License: MIT
Keywords: python,mouse-automation,gui-testing,automation,simulation,mouse,gui,testing
Classifier: Programming Language :: Python :: 3
Classifier: Operating System :: MacOS :: MacOS X
Classifier: Operating System :: Microsoft :: Windows
Classifier: License :: OSI Approved :: MIT License
License-File: LICENSE
Requires-Dist: pyautogui
Requires-Dist: keyboard
Requires-Dist: opencv-python
Requires-Dist: pillow
Requires-Dist: click
Requires-Dist: pyperclip
Requires-Dist: pynput
Requires-Dist: easygui
